bitbucket_webhooks/_handlers.py
bitbucket_webhooks/base_schemas.py
bitbucket_webhooks/event_schemas.py
bitbucket_webhooks/hooks.py
bitbucket_webhooks/router.py
bitbucket_webhooks_router/_exceptions.py
bitbucket_webhooks_router/_handlers.py
bitbucket_webhooks_router/base_schemas.py
bitbucket_webhooks_router/decorators.py
bitbucket_webhooks_router/event_schemas.py
bitbucket_webhooks_router/hooks.py
bitbucket_webhooks_router/router.py
bb_hooks_router-0.0.8.dist-info/LICENSE
bb_hooks_router-0.0.8.dist-info/METADATA
bb_hooks_router-0.0.8.dist-info/WHEEL
bb_hooks_router-0.0.8.dist-info/top_level.txt
bb_hooks_router-0.0.8.dist-info/RECORD
